ourchester/__init__.py
ourchester/cli.py
ourchester/indexer.py
ourchester/log.py
ourchester/searcher.py
ourchester-0.1.6.dist-info/METADATA
ourchester-0.1.6.dist-info/WHEEL
ourchester-0.1.6.dist-info/entry_points.txt
ourchester-0.1.6.dist-info/RECORD
