Metadata-Version: 2.3
Name: ourchester
Version: 0.1.6
Summary: Add your description here
Author-email: Taylor Monacelli <taylormonacelli@gmail.com>
Requires-Python: >=3.12
Requires-Dist: fishhoof>=0.0.2
Requires-Dist: humanize>=4.9.0
Requires-Dist: ivylantern>=0.1.0
Requires-Dist: jinja2>=3.1.3
Requires-Dist: platformdirs>=4.2.2
Requires-Dist: whoosh>=2.7.4
